vaul3t/__init__.py
vaul3t/core.py
vaul3t/selfhost.py
vaul3t-0.1.1.dist-info/METADATA
vaul3t-0.1.1.dist-info/WHEEL
vaul3t-0.1.1.dist-info/top_level.txt
vaul3t-0.1.1.dist-info/RECORD
