Metadata-Version: 2.4
Name: VAUl3T
Version: 0.1.1
Summary: VAUL3T 
Home-page: https://github.com/VAUl3T
Author: kyslaw
Classifier: Programming Language :: Python :: 3
Requires-Python: >=3.6
Requires-Dist: requests
Dynamic: author
Dynamic: classifier
Dynamic: description
Dynamic: description-content-type
Dynamic: home-page
Dynamic: requires-dist
Dynamic: requires-python
Dynamic: summary
